chaosExtractor/__init__.py
chaosExtractor/generator.py
chaosExtractor-1.0.5.dist-info/LICENSE
chaosExtractor-1.0.5.dist-info/METADATA
chaosExtractor-1.0.5.dist-info/WHEEL
chaosExtractor-1.0.5.dist-info/top_level.txt
chaosExtractor-1.0.5.dist-info/RECORD
