Metadata-Version: 2.2
Name: chaosExtractor
Version: 1.0.5
Summary: Multi-package
Home-page: https://sites.google.com/view/pasta-apes/c-h-a-o-s
Author: GeekoSaiyan
Author-email: kreolpony@gmail.com
Classifier: Programming Language :: Python :: 3
Classifier: Operating System :: OS Independent
Requires-Python: >=3.12
License-File: LICENSE
Requires-Dist: requests
Dynamic: author
Dynamic: author-email
Dynamic: classifier
Dynamic: description
Dynamic: description-content-type
Dynamic: home-page
Dynamic: requires-dist
Dynamic: requires-python
Dynamic: summary
